{
  "steps": [
    {
      "dotFilePath": "ExampleNetwork.dot",
      "isDirected": true,
      "createRing": true,
      "createClique": false,
      "createBinTree": false,
      "enableFailureDetector": false,
      "algorithm": "chang-roberts",
      "additionalParameters": {
        "initiators": 5,
        "additional": 0,
        "kill": 1
      }
    },
    {
        "dotFilePath": "ExampleNetwork.dot",
        "isDirected": false,
        "createRing": true,
        "createClique": false,
        "createBinTree": false,
        "enableFailureDetector": false,
        "algorithm": "franklin",
        "additionalParameters": {
            "initiators": 6,
            "additional": 0,
            "kill": 1
        }
    },
    {
      "dotFilePath": "ExampleNetwork.dot",
      "isDirected": true,
      "createRing": true,
      "createClique": false,
      "createBinTree": false,
      "enableFailureDetector": false,
      "algorithm": "dolev-klawe-rodeh",
      "additionalParameters": {
        "initiators": 7,
        "additional": 0,
        "kill": 1
      }
    },
    {
      "dotFilePath": "ExampleNetwork.dot",
      "isDirected": false,
      "createRing": false,
      "createClique": false,
      "createBinTree": false,
      "enableFailureDetector": false,
      "algorithm": "echo-election",
      "additionalParameters": {
        "initiators": 5,
        "additional": 0,
        "kill": 1
      }
    },
    {
      "dotFilePath": "ExampleNetwork.dot",
      "isDirected": false,
      "createRing": false,
      "createClique": false,
      "createBinTree": false,
      "enableFailureDetector": false,
      "algorithm": "tree-election",
      "additionalParameters": {
        "initiators": 7,
        "additional": 0,
        "kill": 1
      }
    }
  ]
}
